<WndTap Name="insure_theftfire_v" Text="insure_theftfire">
<WndTaps>
<xi:include xmlns:xi="http://www.w3.org/2001/XInclude" href="insure_theftfire_Ve.xml" popup="1"/>
</WndTaps>
<xi:include xmlns:xi="http://www.w3.org/2001/XInclude" href="lan\insure_theftfire.xml"/>
<Ctrls><GroupBox  Name="GBinsure_theftfire" id="insure_theftfire" Text="insure_theftfire" Size="100,100"><Ctrls>
<xi:include xmlns:xi="http://www.w3.org/2001/XInclude" href="insure_theftfire_Vs.xml"/>
<BR AutoHeight="1"/><GroupBox  Name="GBOPVinsure_theftfire" Size="100,20" cols="xs12 sm12 md12 lg12"><Ctrls>
<Button Text="addone" ToolTip="ttp_addone" Name="addone" Size="50,20">	<OnClick><submit next="$this.insure_theftfire.GBDEDITinsure_theftfire" function="reset"/></OnClick>	</Button><TAB/>	
<Button Text="reset" ToolTip="ttp_resetinsure_theftfire" Name="resetinsure_theftfire" Size="50,20">	<OnClick>	<submit next="GBDEDITinsure_theftfire" function="reset"/>	</OnClick>	</Button><TAB/>	
<Button Text="gsearch" ToolTip="ttp_gsearchinsure_theftfire" Name="gsearchinsure_theftfire" Size="50,20" visible="true">	<OnClick>	<search next="insure_theftfire_vLst" listed="0" prefixwhere="0" inputed="1"></search><submit next="GBDEDITinsure_theftfire" namelist="search" function="search"/>	</OnClick>	</Button><TAB/></Ctrls></GroupBox>
<BR AutoHeight="1"/><xi:include xmlns:xi="http://www.w3.org/2001/XInclude" href="insure_theftfire_Vv.xml"/>
</Ctrls></GroupBox>
</Ctrls></WndTap>
